vieneu/__init__.py
vieneu/core.py
vieneu/serve.py
vieneu/assets/samples/Bình (nam miền Bắc).pt
vieneu/assets/samples/Bình (nam miền Bắc).txt
vieneu/assets/samples/Bình (nam miền Bắc).wav
vieneu/assets/samples/Ly (nữ miền Bắc).pt
vieneu/assets/samples/Ly (nữ miền Bắc).txt
vieneu/assets/samples/Ly (nữ miền Bắc).wav
vieneu/assets/samples/Ngọc (nữ miền Bắc).pt
vieneu/assets/samples/Ngọc (nữ miền Bắc).txt
vieneu/assets/samples/Ngọc (nữ miền Bắc).wav
vieneu/assets/samples/Tuyên (nam miền Bắc).pt
vieneu/assets/samples/Tuyên (nam miền Bắc).txt
vieneu/assets/samples/Tuyên (nam miền Bắc).wav
vieneu/assets/samples/Vĩnh (nam miền Nam).pt
vieneu/assets/samples/Vĩnh (nam miền Nam).txt
vieneu/assets/samples/Vĩnh (nam miền Nam).wav
vieneu/assets/samples/Đoan (nữ miền Nam).pt
vieneu/assets/samples/Đoan (nữ miền Nam).txt
vieneu/assets/samples/Đoan (nữ miền Nam).wav
vieneu-1.1.7.dist-info/licenses/LICENSE
vieneu_utils/__init__.py
vieneu_utils/core_utils.py
vieneu_utils/normalize_text.py
vieneu_utils/phoneme_dict.json
vieneu_utils/phonemize_text.py
vieneu-1.1.7.dist-info/METADATA
vieneu-1.1.7.dist-info/WHEEL
vieneu-1.1.7.dist-info/top_level.txt
vieneu-1.1.7.dist-info/RECORD
