Metadata-Version: 2.4
Name: vieneu
Version: 1.1.7
Summary: Advanced on-device Vietnamese TTS with instant voice cloning
Author-email: Phạm Nguyễn Ngọc Bảo <pnnbao@gmail.com>
License:                                  Apache License
Project-URL: Homepage, https://github.com/pnnbao97/VieNeu-TTS
Project-URL: Repository, https://github.com/pnnbao97/VieNeu-TTS
Project-URL: Bug Tracker, https://github.com/pnnbao97/VieNeu-TTS/issues
Project-URL: Documentation, https://github.com/pnnbao97/VieNeu-TTS/blob/main/README.md
Project-URL: Source Code, https://github.com/pnnbao97/VieNeu-TTS
Project-URL: Changelog, https://github.com/pnnbao97/VieNeu-TTS/releases
Keywords: text-to-speech,tts,vietnamese,voice-cloning,speech-synthesis,real-time,on-device
Classifier: Development Status :: 4 - Beta
Classifier: Intended Audience :: Developers
Classifier: Intended Audience :: Science/Research
Classifier: License :: OSI Approved :: Apache Software License
Classifier: Programming Language :: Python :: 3.10
Classifier: Programming Language :: Python :: 3.11
Classifier: Programming Language :: Python :: 3.12
Classifier: Programming Language :: Python :: 3.13
Classifier: Topic :: Multimedia :: Sound/Audio :: Speech
Classifier: Topic :: Scientific/Engineering :: Artificial Intelligence
Classifier: Operating System :: OS Independent
Requires-Python: >=3.10
License-File: LICENSE
Requires-Dist: phonemizer>=3.3.0
Requires-Dist: neucodec>=0.0.4
Requires-Dist: librosa>=0.11.0
Requires-Dist: gradio>=5.49.1
Requires-Dist: onnxruntime>=1.23.2
Requires-Dist: datasets>=3.2.0
Requires-Dist: torch
Requires-Dist: torchaudio
Requires-Dist: perth>=0.2.0
Requires-Dist: llama-cpp-python==0.3.16
Requires-Dist: requests
Provides-Extra: gpu
Requires-Dist: lmdeploy; sys_platform != "darwin" and extra == "gpu"
Requires-Dist: triton-windows; sys_platform == "win32" and extra == "gpu"
Requires-Dist: triton; sys_platform == "linux" and extra == "gpu"
Requires-Dist: transformers; sys_platform == "darwin" and extra == "gpu"
Requires-Dist: accelerate; sys_platform == "darwin" and extra == "gpu"
Dynamic: license-file
